md5hash/__init__.py
md5hash/md5hash.py
md5hash-0.0.6.dist-info/LICENSE
md5hash-0.0.6.dist-info/METADATA
md5hash-0.0.6.dist-info/WHEEL
md5hash-0.0.6.dist-info/top_level.txt
md5hash-0.0.6.dist-info/RECORD
