Metadata-Version: 2.1
Name: md5hash
Version: 0.0.6
Summary: Fast and simple md5 hash generator for files and directories
Home-page: https://github.com/valsaven/md5hash/
Author: Val Saven
Author-email: val.saven@gmail.com
License: MIT License
Keywords: md5
Platform: UNKNOWN
Requires: Python (>= 3.5)
